supportLibEasyT/__init__.py
supportLibEasyT/log_manager.py
supportLibEasyT-0.1.0.dist-info/METADATA
supportLibEasyT-0.1.0.dist-info/WHEEL
supportLibEasyT-0.1.0.dist-info/top_level.txt
supportLibEasyT-0.1.0.dist-info/RECORD
