Metadata-Version: 2.1
Name: supportLibEasyT
Version: 0.1.0
Summary: UNKNOWN
Home-page: UNKNOWN
Author: Joao Paulo Euko
License: MIT
Platform: UNKNOWN
